livn/__init__.py
livn/cli.py
livn/env.py
livn/io.py
livn/stimulus.py
livn/system.py
livn/types.py
livn/utils.py
livn/backend/__init__.py
livn/backend/common.py
livn/backend/config.py
livn/backend/brian2/__init__.py
livn/backend/diffrax/__init__.py
livn/backend/neuron/__init__.py
livn/integrations/gym.py
livn/models/izhikevich.py
livn/models/lif.py
livn/models/rcsd/__init__.py
livn/models/rcsd/neuron/mechanisms/Gfluct2.mod
livn/models/rcsd/neuron/mechanisms/Gfluct3.mod
livn/models/rcsd/neuron/mechanisms/Ifluct1.mod
livn/models/rcsd/neuron/mechanisms/cacumm.mod
livn/models/rcsd/neuron/mechanisms/cagk.mod
livn/models/rcsd/neuron/mechanisms/cal2.mod
livn/models/rcsd/neuron/mechanisms/can2.mod
livn/models/rcsd/neuron/mechanisms/cat.mod
livn/models/rcsd/neuron/mechanisms/kaprox.mod
livn/models/rcsd/neuron/mechanisms/kd.mod
livn/models/rcsd/neuron/mechanisms/kd_inc_tau.mod
livn/models/rcsd/neuron/mechanisms/kdrca1.mod
livn/models/rcsd/neuron/mechanisms/km.mod
livn/models/rcsd/neuron/mechanisms/lin_exp2syn.mod
livn/models/rcsd/neuron/mechanisms/lin_exp2synNMDA.mod
livn/models/rcsd/neuron/mechanisms/na3n.mod
livn/models/rcsd/neuron/mechanisms/vecevent.mod
livn/models/rcsd/neuron/mechanisms/BR/CaL.mod
livn/models/rcsd/neuron/mechanisms/BR/CaN.mod
livn/models/rcsd/neuron/mechanisms/BR/Ca_conc.mod
livn/models/rcsd/neuron/mechanisms/BR/KCa.mod
livn/models/rcsd/neuron/mechanisms/BR/K_conc.mod
livn/models/rcsd/neuron/mechanisms/BR/Kdr.mod
livn/models/rcsd/neuron/mechanisms/BR/Na_conc.mod
livn/models/rcsd/neuron/mechanisms/BR/Nap.mod
livn/models/rcsd/neuron/mechanisms/BR/Nas.mod
livn/models/rcsd/neuron/mechanisms/BR/constant.mod
livn/models/rcsd/neuron/mechanisms/PR/Ca_PR.mod
livn/models/rcsd/neuron/mechanisms/PR/Ca_conc_PR.mod
livn/models/rcsd/neuron/mechanisms/PR/KCa_PR.mod
livn/models/rcsd/neuron/mechanisms/PR/K_PR.mod
livn/models/rcsd/neuron/mechanisms/PR/K_conc_PR.mod
livn/models/rcsd/neuron/mechanisms/PR/Na_PR.mod
livn/models/rcsd/neuron/mechanisms/PR/Na_conc_PR.mod
livn-0.1.0.dist-info/METADATA
livn-0.1.0.dist-info/WHEEL
livn-0.1.0.dist-info/entry_points.txt
livn-0.1.0.dist-info/licenses/LICENSE.txt
livn-0.1.0.dist-info/RECORD
