Metadata-Version: 2.4
Name: livn
Version: 0.1.0
Summary: A testbed for learning to interact with in vitro neural networks
Author-email: Frithjof Gressmann <fg14@illinois.edu>, Ivan Raikov <ivan.g.raikov@gmail.com>
License-File: LICENSE.txt
Requires-Python: >=3.11
Requires-Dist: cleosim>=0.16.0
Requires-Dist: gymnasium>=1.1.1
Requires-Dist: huggingface-hub[cli]>=0.3.1
Requires-Dist: jaxtyping>=0.2.34
Requires-Dist: pandas>=2.2.3
Requires-Dist: pyarrow>=19.0.1
Requires-Dist: pydantic>=2.11.3
